bucky/__init__.py
bucky/__main__.py
bucky/_typing.py
bucky/base_config/00_data.yml
bucky/base_config/00_default.yml
bucky/base_config/00_feature_flags.yml
bucky/base_config/00_historical_fitting.yml
bucky/base_config/00_model_structure.yml
bucky/base_config/00_monte_carlo_postprocessing.yml
bucky/base_config/00_system.yml
bucky/cli/__init__.py
bucky/cli/__main__.py
bucky/cli/cfg.py
bucky/cli/data.py
bucky/cli/main.py
bucky/cli/run.py
bucky/cli/typer_utils.py
bucky/cli/viz.py
bucky/config.py
bucky/data/__init__.py
bucky/data/adm_mapping.py
bucky/data/clean_historical_data.py
bucky/data/timeseries.py
bucky/datasource_transforms/__init__.py
bucky/datasource_transforms/bin_bridged_race_census_csv.py
bucky/datasource_transforms/csse_timeseries.py
bucky/datasource_transforms/extract_shapefile_data.py
bucky/datasource_transforms/hhs_hosp_cleanup.py
bucky/datasource_transforms/prem_2020_csv.py
bucky/exceptions.py
bucky/included_data/adm2_phased_age_dists.p
bucky/included_data/lookup_tables/CONUS_county.lookup
bucky/included_data/lookup_tables/CONUS_state.lookup
bucky/included_data/lookup_tables/DMV.lookup
bucky/included_data/population/territory_pop.csv
bucky/included_data/state_update.yml
bucky/included_data/statefips_to_names.csv
bucky/included_data/us_adm1_abbrev_map.csv
bucky/included_data/vaccine_hesitancy/vaccine_hesitancy_all_cols.csv
bucky/included_data/vaccine_hesitancy/vaccine_hesitancy_all_cols_se.csv
bucky/model/__init__.py
bucky/model/adjmat.py
bucky/model/data.py
bucky/model/derived_epi_params.py
bucky/model/estimation.py
bucky/model/exceptions.py
bucky/model/io.py
bucky/model/main.py
bucky/model/mc_instance.py
bucky/model/npi.py
bucky/model/rhs.py
bucky/model/state.py
bucky/model/vacc.py
bucky/model/vacc2.py
bucky/numerical_libs.py
bucky/postprocess.py
bucky/util/__init__.py
bucky/util/array_utils.py
bucky/util/async_thread.py
bucky/util/cached_prop.py
bucky/util/data_sync.py
bucky/util/detect_cupy.py
bucky/util/distributions.py
bucky/util/extrapolate.py
bucky_covid-1.0.0a0.post2.dist-info/entry_points.txt
bucky_covid-1.0.0a0.post2.dist-info/LICENSE
bucky_covid-1.0.0a0.post2.dist-info/WHEEL
bucky_covid-1.0.0a0.post2.dist-info/METADATA
bucky_covid-1.0.0a0.post2.dist-info/RECORD
