Metadata-Version: 2.1
Name: bucky-covid
Version: 1.0.0a0.post2
Summary: The Bucky model is a spatial SEIR model for simulating COVID-19 at the county level.
Home-page: https://buckymodel.com
Keywords: bucky,covid,covid19,model,epi
Author: Matt Kinsey
Author-email: matt@mkinsey.com
Requires-Python: >=3.8,<3.11
Classifier: Development Status :: 4 - Beta
Classifier: Intended Audience :: Developers
Classifier: License :: OSI Approved :: MIT License
Classifier: Natural Language :: English
Classifier: Programming Language :: Python :: 3
Classifier: Programming Language :: Python :: 3.10
Classifier: Programming Language :: Python :: 3.7
Classifier: Programming Language :: Python :: 3.8
Classifier: Programming Language :: Python :: 3.9
Requires-Dist: PyQt5 (>=5.15.6,<6.0.0)
Requires-Dist: better-exceptions (>=0.3.3,<0.4.0)
Requires-Dist: cupy (>=10.5.0,<11.0.0)
Requires-Dist: fastparquet (>=0.8.1,<0.9.0)
Requires-Dist: geopandas (>=0.10.2,<0.11.0)
Requires-Dist: joblib (>=1.1.0,<2.0.0)
Requires-Dist: loguru (>=0.6.0,<0.7.0)
Requires-Dist: matplotlib (>=3.5.2,<4.0.0)
Requires-Dist: numpy (>=1.22.4,<2.0.0)
Requires-Dist: optuna (>=2.10.0,<3.0.0)
Requires-Dist: pandas (>=1.4.2,<2.0.0)
Requires-Dist: ruamel.yaml (>=0.17.21,<0.18.0)
Requires-Dist: scikit-optimize (>=0.9.0,<0.10.0)
Requires-Dist: scipy (>=1.8.1,<2.0.0)
Requires-Dist: tqdm (>=4.64.0,<5.0.0)
Requires-Dist: typer (>=0.4.1,<0.5.0)
Requires-Dist: us (>=2.0.2,<3.0.0)
Project-URL: Repository, https://github.com/mattkinsey/bucky
